<!--
    Waypoints for: Mediah Adventure Log V
    Created by: flockenberger
-->
<WorldmapBookMark>
    <BookMark BookMarkName="Those Who See Kamasylve" PosX="-241610.0" PosY="15382.7001953125" PosZ="-330391.0" />
    <BookMark BookMarkName="Dorin Morgrim and the Advance of the Helms" PosX="-241610.0" PosY="15382.7001953125" PosZ="-330391.0" />
    <BookMark BookMarkName="Blast from the Lava Cave and Alien Creatures" PosX="-241610.0" PosY="15382.7001953125" PosZ="-330391.0" />
    <BookMark BookMarkName="Illezra and the Bound" PosX="-241610.0" PosY="15382.7001953125" PosZ="-330391.0" />
    <BookMark BookMarkName="Sand Storm and the Three Day Disaster" PosX="-241610.0" PosY="15382.7001953125" PosZ="-330391.0" />
    <BookMark BookMarkName="On the Ancient Ground" PosX="-241610.0" PosY="15382.7001953125" PosZ="-330391.0" />
    <BookMark BookMarkName="Remembering the Royal Parade" PosX="-241610.0" PosY="15382.7001953125" PosZ="-330391.0" />
    <BookMark BookMarkName="The Fall of the Royal Family and the Remnants" PosX="-241610.0" PosY="15382.7001953125" PosZ="-330391.0" />
    <BookMark BookMarkName="The Evil of Necromancy" PosX="-241610.0" PosY="15382.7001953125" PosZ="-330391.0" />
    <BookMark BookMarkName="Tale of the Ancient Giants and Tantu" PosX="-241610.0" PosY="15382.7001953125" PosZ="-330391.0" />
    <BookMark BookMarkName="Power That Moved the Ancient Civilization Forward" PosX="154485.0" PosY="6336.83984375" PosZ="11086.0" />
</WorldmapBookMark>