<!--
    Waypoints for: O'dyllita Forest Adventure Log
    Created by: flockenberger
-->
<WorldmapBookMark>
    <BookMark BookMarkName="Something's Nest" PosX="-120424.0" PosY="27945.900390625" PosZ="-580078.0" />
    <BookMark BookMarkName="Book of Josya" PosX="-120424.0" PosY="27945.900390625" PosZ="-580078.0" />
    <BookMark BookMarkName="Research on the Fallen" PosX="-120424.0" PosY="27945.900390625" PosZ="-580078.0" />
    <BookMark BookMarkName="Bahitram Villager's Book" PosX="-120424.0" PosY="27945.900390625" PosZ="-580078.0" />
    <BookMark BookMarkName="Lighthouse of the Valley" PosX="-120424.0" PosY="27945.900390625" PosZ="-580078.0" />
    <BookMark BookMarkName="Orzeca Lightstone" PosX="-120424.0" PosY="27945.900390625" PosZ="-580078.0" />
    <BookMark BookMarkName="Wanderer's Bonfire" PosX="-120424.0" PosY="27945.900390625" PosZ="-580078.0" />
    <BookMark BookMarkName="Adventurer's Bonfire" PosX="-120424.0" PosY="27945.900390625" PosZ="-580078.0" />
    <BookMark BookMarkName="Thornwood Goddess Statue VII" PosX="-120424.0" PosY="27945.900390625" PosZ="-580078.0" />
    <BookMark BookMarkName="Azure Flame" PosX="-120424.0" PosY="27945.900390625" PosZ="-580078.0" />
    <BookMark BookMarkName="Hadum God of Despair III" PosX="-120424.0" PosY="27945.900390625" PosZ="-580078.0" />
    <BookMark BookMarkName="Hadum God of Despair II" PosX="-120424.0" PosY="27945.900390625" PosZ="-580078.0" />
    <BookMark BookMarkName="Hadum God of Despair I" PosX="-120424.0" PosY="27945.900390625" PosZ="-580078.0" />
    <BookMark BookMarkName="Empty Coffin" PosX="-120424.0" PosY="27945.900390625" PosZ="-580078.0" />
    <BookMark BookMarkName="Thornwood Goddess Statue VI" PosX="-120424.0" PosY="27945.900390625" PosZ="-580078.0" />
    <BookMark BookMarkName="Thornwood Goddess Statue V" PosX="-120424.0" PosY="27945.900390625" PosZ="-580078.0" />
    <BookMark BookMarkName="Thornwood Goddess Statue IV" PosX="-120424.0" PosY="27945.900390625" PosZ="-580078.0" />
    <BookMark BookMarkName="Commandments of Truth #5" PosX="-120424.0" PosY="27945.900390625" PosZ="-580078.0" />
    <BookMark BookMarkName="Commandments of Truth #4" PosX="-120424.0" PosY="27945.900390625" PosZ="-580078.0" />
    <BookMark BookMarkName="Thornwood Goddess Statue III" PosX="-120424.0" PosY="27945.900390625" PosZ="-580078.0" />
    <BookMark BookMarkName="Thornwood Goddess Statue II" PosX="-120424.0" PosY="27945.900390625" PosZ="-580078.0" />
    <BookMark BookMarkName="Thornwood Goddess Statue I" PosX="-120424.0" PosY="27945.900390625" PosZ="-580078.0" />
    <BookMark BookMarkName="Tunkuta Springs" PosX="-120424.0" PosY="27945.900390625" PosZ="-580078.0" />
    <BookMark BookMarkName="Neglected Maps" PosX="-120424.0" PosY="27945.900390625" PosZ="-580078.0" />
    <BookMark BookMarkName="Commandments of Truth #3" PosX="-120424.0" PosY="27945.900390625" PosZ="-580078.0" />
    <BookMark BookMarkName="Empty Altar" PosX="-120424.0" PosY="27945.900390625" PosZ="-580078.0" />
    <BookMark BookMarkName="Tree of Prayer" PosX="-120424.0" PosY="27945.900390625" PosZ="-580078.0" />
    <BookMark BookMarkName="Breath of Narcion" PosX="-120424.0" PosY="27945.900390625" PosZ="-580078.0" />
    <BookMark BookMarkName="Map of O'dyllita" PosX="-120424.0" PosY="27945.900390625" PosZ="-580078.0" />
    <BookMark BookMarkName="On Reincarnation" PosX="-120424.0" PosY="27945.900390625" PosZ="-580078.0" />
    <BookMark BookMarkName="Knowledge of the Goddess Song" PosX="-120424.0" PosY="27945.900390625" PosZ="-580078.0" />
    <BookMark BookMarkName="Knowledge of the Goddess Protection" PosX="-120424.0" PosY="27945.900390625" PosZ="-580078.0" />
    <BookMark BookMarkName="Knowledge of the Goddess Light" PosX="-120424.0" PosY="27945.900390625" PosZ="-580078.0" />
    <BookMark BookMarkName="Quturan's Fruit" PosX="-120424.0" PosY="27945.900390625" PosZ="-580078.0" />
    <BookMark BookMarkName="Shadow Snake" PosX="-120424.0" PosY="27945.900390625" PosZ="-580078.0" />
    <BookMark BookMarkName="Commandments of Truth #11" PosX="-120424.0" PosY="27945.900390625" PosZ="-580078.0" />
    <BookMark BookMarkName="Commandments of Truth #10" PosX="-120424.0" PosY="27945.900390625" PosZ="-580078.0" />
    <BookMark BookMarkName="Commandments of Truth #9" PosX="-120424.0" PosY="27945.900390625" PosZ="-580078.0" />
    <BookMark BookMarkName="Commandments of Truth #8" PosX="-120424.0" PosY="27945.900390625" PosZ="-580078.0" />
    <BookMark BookMarkName="Commandments of Truth #7" PosX="-120424.0" PosY="27945.900390625" PosZ="-580078.0" />
    <BookMark BookMarkName="Commandments of Truth #6" PosX="-120424.0" PosY="27945.900390625" PosZ="-580078.0" />
    <BookMark BookMarkName="Festival of the Sun and Moon" PosX="-120424.0" PosY="27945.900390625" PosZ="-580078.0" />
    <BookMark BookMarkName="Choice and Survival" PosX="-120424.0" PosY="27945.900390625" PosZ="-580078.0" />
    <BookMark BookMarkName="Unknown Test Flask" PosX="-120424.0" PosY="27945.900390625" PosZ="-580078.0" />
    <BookMark BookMarkName="Audrite Doctrine" PosX="-120424.0" PosY="27945.900390625" PosZ="-580078.0" />
    <BookMark BookMarkName="Commandments of Truth #2" PosX="-120424.0" PosY="27945.900390625" PosZ="-580078.0" />
    <BookMark BookMarkName="Commandments of Truth #1" PosX="-120424.0" PosY="27945.900390625" PosZ="-580078.0" />
</WorldmapBookMark>