<!--
    Waypoints for: Officials of Donghae Province
    Created by: flockenberger
-->
<WorldmapBookMark>
    <BookMark BookMarkName="Heosun " PosX="-1092740.0" PosY="5764.66015625" PosZ="1113920.0" />
    <BookMark BookMarkName="Gapdol" PosX="-1291610.0" PosY="-7695.97998046875" PosZ="1133460.0" />
    <BookMark BookMarkName="Insong" PosX="-1141900.0" PosY="18073.400390625" PosZ="1282690.0" />
    <BookMark BookMarkName="Yooshin" PosX="-1299090.0" PosY="-7337.08984375" PosZ="1141510.0" />
    <BookMark BookMarkName="Yibang" PosX="-1140080.0" PosY="18001.19921875" PosZ="1282230.0" />
    <BookMark BookMarkName="Jang Iksoon" PosX="-1139950.0" PosY="18161.900390625" PosZ="1282800.0" />
    <BookMark BookMarkName="Lee Duksoo" PosX="-1292850.0" PosY="-3981.52001953125" PosZ="1155150.0" />
    <BookMark BookMarkName="Moon Bakbeol" PosX="-1290940.0" PosY="-4736.31005859375" PosZ="1147550.0" />
    <BookMark BookMarkName="Yang Boksoo" PosX="-1289038.625" PosY="-4022.070068359375" PosZ="1150661.125" />
</WorldmapBookMark>