<!--
    Waypoints for: Marine Food
    Created by: flockenberger
-->
<WorldmapBookMark>
    <BookMark BookMarkName="Seagull Egg" PosX="22008.599609375" PosY="-6342.91015625" PosZ="76542.6015625" />
    <BookMark BookMarkName="Dried Herb Leaf" PosX="22008.599609375" PosY="-6342.91015625" PosZ="76542.6015625" />
    <BookMark BookMarkName="Louruvian Oyster" PosX="22008.599609375" PosY="-6342.91015625" PosZ="76542.6015625" />
    <BookMark BookMarkName="Clam Box" PosX="22008.599609375" PosY="-6342.91015625" PosZ="76542.6015625" />
    <BookMark BookMarkName="Coarse Sun-Dried Salt" PosX="22008.599609375" PosY="-6342.91015625" PosZ="76542.6015625" />
    <BookMark BookMarkName="Gentian Wine" PosX="22008.599609375" PosY="-6342.91015625" PosZ="76542.6015625" />
    <BookMark BookMarkName="Caviar" PosX="22008.599609375" PosY="-6342.91015625" PosZ="76542.6015625" />
    <BookMark BookMarkName="Whole King Crab" PosX="22008.599609375" PosY="-6342.91015625" PosZ="76542.6015625" />
    <BookMark BookMarkName="Exotic Spice" PosX="22008.599609375" PosY="-6342.91015625" PosZ="76542.6015625" />
</WorldmapBookMark>