<!--
    Waypoints for: Sophistication I
    Created by: flockenberger
-->
<WorldmapBookMark>
    <BookMark BookMarkName="A Velian Epic" PosX="-126517.0" PosY="-1414.8699951171875" PosZ="121655.0" />
    <BookMark BookMarkName="The Flute Boy" PosX="36989.1015625" PosY="-2839.889892578125" PosZ="-43024.8984375" />
    <BookMark BookMarkName="Witch at the Farm" PosX="9633.7197265625" PosY="1496.8499755859375" PosZ="-14916.7001953125" />
    <BookMark BookMarkName="The Cook's Presence" PosX="-132235.0" PosY="24765.400390625" PosZ="-329096.0" />
    <BookMark BookMarkName="Artemio the Literary Lion" PosX="7110.16015625" PosY="-6524.66015625" PosZ="71263.796875" />
    <BookMark BookMarkName="Olivia: A Travel Sketch" PosX="-132235.0" PosY="24765.400390625" PosZ="-329096.0" />
    <BookMark BookMarkName="An Epic Romance" PosX="41242.19921875" PosY="-2879.419921875" PosZ="-44977.69921875" />
    <BookMark BookMarkName="Living a Leader" PosX="-126517.0" PosY="-1414.8699951171875" PosZ="121655.0" />
    <BookMark BookMarkName="Wall Climbing" PosX="14842.0" PosY="-6310.2998046875" PosZ="84176.703125" />
    <BookMark BookMarkName="Mysterious Sculptor" PosX="-118394.0" PosY="3050.0" PosZ="-182635.0" />
    <BookMark BookMarkName="How to Survive Monster Attacks" PosX="37507.19921875" PosY="-1026.010009765625" PosZ="-134171.0" />
    <BookMark BookMarkName="Velia Specialties" PosX="38530.8984375" PosY="-995.7860107421875" PosZ="-29238.19921875" />
    <BookMark BookMarkName="Berman's Cooking Secrets" PosX="38842.6015625" PosY="-410.4750061035156" PosZ="-12015.7998046875" />
    <BookMark BookMarkName="Serendia: The Glorious History" PosX="-59655.80078125" PosY="-3816.3701171875" PosZ="39264.69921875" />
    <BookMark BookMarkName="Travels in Mediah" PosX="-22097.599609375" PosY="534.2940063476562" PosZ="-120674.0" />
    <BookMark BookMarkName="Meister Lomerun" PosX="-132817.0" PosY="24779.19921875" PosZ="-329164.0" />
</WorldmapBookMark>